{
  "target_name": "考研",
  "target_date": "2026-12-21",
  "city": "郑州",
  "focus_min": 1,
  "break_min": 1,
  "tomatoes": 1,
  "tasks": [],
  "daily_stats": {
    "2025-12-06": 5,
    "2025-12-07": 1
  },
  "countdowns": [],
  "history": [
    "[2025-12-06 00:42] 完成专注 🍅",
    "[2025-12-06 00:56] 抓到一个番茄 🍅",
    "[2025-12-06 01:37] 抓到一个番茄 🍅",
    "[2025-12-06 12:24] 抓到一个番茄 🍅",
    "[2025-12-06 12:32] 🗑️ 移除倒计时: 123",
    "[2025-12-06 12:32] ✅ 完成任务: 2025-12-06 // 1 // 123",
    "[2025-12-06 12:32] ✅ 完成任务: 2025-12-06 🐾 2. eqweqw",
    "[14:52] 爪子一挥，完成: 51325",
    "[14:52] 爪子一挥，完成: 412",
    "[14:52] 爪子一挥，完成: 31123",
    "[15:25] 捕获一只番茄 🍅 (嚼嚼嚼)",
    "[17:48] 捕获一只番茄 🍅 (嚼嚼嚼)",
    "[17:53] 捕获一只番茄 🍅 (嚼嚼嚼)",
    "[18:03] 捕获一只番茄 🍅 (嚼嚼嚼)",
    "[20:45] 捕获一只番茄 🍅 (嚼嚼嚼)",
    "[00:02] 🐾 按下今日爪印",
    "[09:56] 捕获一只番茄 🍅 (嚼嚼嚼)",
    "[10:13] 爪子一挥，完成: eqweq"
  ],
  "last_checkin": "2025-12-07",
  "streak_days": 2
}